blockchain_payment_mcp/__init__.py
blockchain_payment_mcp/blockchain.py
blockchain_payment_mcp/config.py
blockchain_payment_mcp/multi_chain.py
blockchain_payment_mcp/server.py
blockchain_payment_mcp/wallet.py
blockchain_payment_mcp-0.1.12.dist-info/METADATA
blockchain_payment_mcp-0.1.12.dist-info/WHEEL
blockchain_payment_mcp-0.1.12.dist-info/entry_points.txt
blockchain_payment_mcp-0.1.12.dist-info/top_level.txt
blockchain_payment_mcp-0.1.12.dist-info/RECORD
