Metadata-Version: 2.4
Name: blockchain-payment-mcp
Version: 0.1.12
Summary: 区块链货币支付MCP服务器
Author-email: liuyuanjie <ai@example.com>
Requires-Python: >=3.8
Requires-Dist: mcp<2.0.0,>=1.13.0
Requires-Dist: web3>=6.0.0
Requires-Dist: cryptography>=3.0.0
Requires-Dist: python-dotenv>=0.19.0
Requires-Dist: pydantic>=2.0.0
Requires-Dist: asyncio-throttle>=1.0.0
Provides-Extra: dev
Requires-Dist: pytest>=7.0.0; extra == "dev"
Requires-Dist: black>=22.0.0; extra == "dev"
Requires-Dist: isort>=5.0.0; extra == "dev"
Requires-Dist: mypy>=1.0.0; extra == "dev"
